README.md
setup.py
pformat/__init__.py
pformat/base.py
pformat/core.py
pformat.egg-info/PKG-INFO
pformat.egg-info/SOURCES.txt
pformat.egg-info/dependency_links.txt
pformat.egg-info/requires.txt
pformat.egg-info/top_level.txt