Metadata-Version: 1.0
Name: pformat
Version: 0.0.1
Summary: Advanced python string formatting
Home-page: UNKNOWN
Author: Bea Steers
Author-email: bea.steers@gmail.com
License: MIT License
Keywords: string format partial glob regex default
Platform: UNKNOWN
